[{"id": 2, "text": "TRẠM Y TẾ XÃ BÌNH NGHĨA", "label": "other", "box": [28, 58, 250, 76]}, {"id": 3, "text": "Số phiếu 745/2018", "label": "other", "box": [372, 91, 525, 123]}, {"id": 4, "text": "4651126", "label": "other", "box": [626, 100, 688, 118]}, {"id": 5, "text": "TOA THUỐC BHYT", "label": "other", "box": [260, 122, 508, 152]}, {"id": 8, "text": "Nam", "label": "other", "box": [620, 160, 655, 177]}, {"id": 9, "text": "Nữ", "label": "other", "box": [685, 160, 708, 177]}, {"id": 12, "text": "35", "label": "other", "box": [300, 207, 322, 225]}, {"id": 13, "text": "35", "label": "other", "box": [366, 207, 387, 225]}, {"id": 14, "text": "205", "label": "other", "box": [436, 207, 468, 225]}, {"id": 15, "text": "46409", "label": "other", "box": [511, 207, 560, 225]}, {"id": 16, "text": "MMHg Thân nhiệt:", "label": "other", "box": [450, 231, 595, 255]}, {"id": 17, "text": "lần/phút Huyết áp:", "label": "other", "box": [168, 232, 305, 252]}, {"id": 18, "text": "Mạch:", "label": "other", "box": [28, 234, 73, 250]}, {"id": 19, "text": "Cận lâm sàng:", "label": "other", "box": [28, 254, 125, 274]}, {"id": 20, "text": "Chấn đoán: J31 - Viêm mũi, viêm mũi họng, viêm họng mạn", "label": "diagnose", "box": [28, 274, 438, 294]}, {"id": 21, "text": "1) CEFACYL 500 0,5g", "label": "drugname", "box": [46, 387, 274, 412], "mapping": 26}, {"id": 22, "text": "SL: 20 Viên", "label": "quantity", "box": [595, 387, 708, 409]}, {"id": 23, "text": "Ghi chú Uống:", "label": "other", "box": [34, 411, 161, 436]}, {"id": 24, "text": "Tối 2 Viên", "label": "usage", "box": [625, 414, 700, 433]}, {"id": 25, "text": "Sáng 2 Viên", "label": "usage", "box": [289, 416, 376, 436]}, {"id": 26, "text": "2) PARTAMOL TAB. 500mg", "label": "drugname", "box": [45, 438, 334, 466], "mapping": 91}, {"id": 27, "text": "SL: 10 viên", "label": "quantity", "box": [595, 439, 703, 461]}, {"id": 28, "text": "Ghi chú Uống:", "label": "other", "box": [34, 463, 161, 488]}, {"id": 29, "text": "Tối 1 viên", "label": "usage", "box": [625, 466, 697, 484]}, {"id": 30, "text": "Sáng 1 viên", "label": "usage", "box": [289, 468, 372, 488]}, {"id": 31, "text": "Cộng khoản: 2 khoản", "label": "other", "box": [33, 496, 197, 514]}, {"id": 32, "text": "Lời dặn đơn thuốc:", "label": "other", "box": [33, 519, 163, 538]}, {"id": 33, "text": "Ngày hẹn tái khám:", "label": "other", "box": [33, 546, 167, 565]}, {"id": 34, "text": "Ngày 26/02/2018", "label": "date", "box": [484, 581, 621, 600]}, {"id": 35, "text": "Bệnh nhân ký nhận", "label": "other", "box": [65, 600, 198, 618]}, {"id": 36, "text": "Y, Bác sĩ điều trị", "label": "other", "box": [494, 606, 611, 626]}, {"id": 37, "text": "BS...............................................................................................................................................................................................................................................................", "label": "other", "box": [476, 683, 616, 700]}, {"id": 38, "text": "Tái khám xin mang theo đơn, xét nghiệm, phim (nếu có)", "label": "other", "box": [33, 735, 414, 760]}, {"id": 39, "text": "09/05/2021 19:43:02", "label": "other", "box": [586, 777, 730, 794]}]